fuzzycount.py
django_postgres_fuzzycount-0.1.7.dist-info/DESCRIPTION.rst
django_postgres_fuzzycount-0.1.7.dist-info/METADATA
django_postgres_fuzzycount-0.1.7.dist-info/metadata.json
django_postgres_fuzzycount-0.1.7.dist-info/RECORD
django_postgres_fuzzycount-0.1.7.dist-info/top_level.txt
django_postgres_fuzzycount-0.1.7.dist-info/WHEEL
