Metadata-Version: 2.0
Name: django-postgres-fuzzycount
Version: 0.1.7
Summary: A Django model manager providing fast / fuzzy counts for PostgreSQL database tables.
Home-page: http://github.com/stephenmcd/django-postgres-fuzzycount
Author: Stephen McDonald
Author-email: stephen.mc@gmail.com
License: UNKNOWN
Platform: UNKNOWN
Classifier: Development Status :: 5 - Production/Stable
Classifier: Environment :: Web Environment
Classifier: Intended Audience :: Developers
Classifier: Operating System :: OS Independent
Classifier: Programming Language :: Python
Classifier: Programming Language :: Python :: 2.6
Classifier: Programming Language :: Python :: 2.7
Classifier: Programming Language :: Python :: 3
Classifier: Programming Language :: Python :: 3.3
Classifier: Framework :: Django
Classifier: Topic :: Internet :: WWW/HTTP :: Dynamic Content
Classifier: Topic :: Internet :: WWW/HTTP :: Site Management
Requires-Dist: sphinx-me (>=0.1.2)
Requires-Dist: django (>=1.7)
